<package>
  <description brief="glados">

     GLaDOS

  </description>
  <author>Jackie Jin</author>
  <license>BSD</license>
  <review status="unreviewed" notes=""/>
  <url>http://ros.org/wiki/glados</url>
  <depend package="roscpp"/>
  <depend package="rospy"/>
  <!-- message depends -->
  <depend package="std_msgs"/>
  <depend package="nav_msgs"/>
  <depend package="geometry_msgs"/>
  <depend package="tf"/>
  <!-- glados stack depends -->
  <depend package="glados_sensors"/>
  <depend package="libax3500"/>
</package>

